qilin/__init__.py
qilin-0.0.1.dist-info/METADATA
qilin-0.0.1.dist-info/WHEEL
qilin-0.0.1.dist-info/top_level.txt
qilin-0.0.1.dist-info/RECORD
