Metadata-Version: 2.1
Name: qilin
Version: 0.0.1
Summary: qilin library for artificial intelligence research
Home-page: UNKNOWN
Author: Lab
Author-email: UNKNOWN
License: MIT
Platform: UNKNOWN
Classifier: Development Status :: 4 - Beta
Classifier: Programming Language :: Python :: 3
